dynamictableprint/__init__.py
dynamictableprint/dynamicprinter.py
dynamictableprint/squisher.py
dynamictableprint/utils.py
dynamictableprint-1.0.3.dist-info/METADATA
dynamictableprint-1.0.3.dist-info/RECORD
dynamictableprint-1.0.3.dist-info/WHEEL
dynamictableprint-1.0.3.dist-info/top_level.txt
