Metadata-Version: 2.1
Name: dynamictableprint
Version: 1.0.3
Summary: Wrapper around TablePrint to adjust columns to the window size
Home-page: https://github.com/DerekYu177/dynamictableprint
Author: Derek Yu
Author-email: derek-nis@hotmail.com
License: UNKNOWN
Project-URL: Bug Reports, https://github.com/DerekYu177/dynamictableprint/issues
Project-URL: Source, https://github.com/DerekYu177/dynamictableprint/
Keywords: table print display dynamic
Platform: UNKNOWN
Classifier: Development Status :: 3 - Alpha
Classifier: Natural Language :: English
Classifier: Intended Audience :: Developers
Classifier: Intended Audience :: Science/Research
Classifier: Topic :: Text Processing :: General
Classifier: License :: OSI Approved :: MIT License
Classifier: Programming Language :: Python :: 3
Classifier: Programming Language :: Python :: 3.4
Classifier: Programming Language :: Python :: 3.5
Classifier: Programming Language :: Python :: 3.6
Provides-Extra: test
Provides-Extra: dev
Requires-Dist: tableprint
Provides-Extra: dev
Requires-Dist: pandas; extra == 'dev'
Provides-Extra: test
Requires-Dist: unittest; extra == 'test'
Requires-Dist: pytest; extra == 'test'
